[
    {
        "todo": "test - 29 Septiembre",
        "delivery_date": null,
        "subject": "Evento de usuario",
        "link": null,
        "description": null
    },
    {
        "todo": "test - 30 Septiembre",
        "delivery_date": null,
        "subject": "Evento de usuario",
        "link": null,
        "description": null
    },
    {
        "todo": "Vencimiento de Inscripción TFG (antes de la subasta)",
        "delivery_date": "viernes, 30 septiembre, 23:59",
        "subject": "2022-23 Projecte final de grau en Enginyeria Multimèdia Gr.A (34844)",
        "link": "https://aulavirtual.uv.es/mod/assign/view.php?id=1267017&action=editsubmission",
        "description": "Debes entregar en pdf la inscripción de tu TFG.Recuerda\n que debes entregar todas las hojas, aunque alguna tengas que dejarla \nsin rellenar (por ejemplo, la de TFG en movilidad o en empresa).El pdf tiene formularios. Debéis entregar el pdf con los formularios rellenos, no escaneado.El impreso debe estar firmado tanto por ti como por tu tutor o tutora. La firma del alumno puede ser firma digital (preferible) o imagen jpg de la firma. La firma del tutor debe ser firma digital.Encontrarás los impresos y normativas en la web de la ETSE."
    },
    {
        "todo": "test - 1 Octubre",
        "delivery_date": null,
        "subject": "Evento de usuario",
        "link": null,
        "description": null
    }
]